GeneAlgPy/__init__.py
GeneAlgPy/basefile.py
GeneAlgPy-0.0.0.dist-info/METADATA
GeneAlgPy-0.0.0.dist-info/WHEEL
GeneAlgPy-0.0.0.dist-info/top_level.txt
GeneAlgPy-0.0.0.dist-info/RECORD
